reps/__init__.py
reps/console.py
reps/hooks.py
reps/templates/base/cookiecutter.json
reps/templates/base/hooks/post_gen_project.py
reps/templates/base/{{cookiecutter.__project_slug}}/.codespell-ignore-words.txt
reps/templates/base/{{cookiecutter.__project_slug}}/.github/CODEOWNERS
reps/templates/base/{{cookiecutter.__project_slug}}/.github/workflows/codeql-analysis.yml
reps/templates/base/{{cookiecutter.__project_slug}}/.pre-commit-config.yaml
reps/templates/base/{{cookiecutter.__project_slug}}/.yamllint.yml
reps/templates/base/{{cookiecutter.__project_slug}}/CODE_OF_CONDUCT.md
reps/templates/base/{{cookiecutter.__project_slug}}/LICENSE
reps/templates/base/{{cookiecutter.__project_slug}}/Makefile
reps/templates/base/{{cookiecutter.__project_slug}}/README.md
reps/templates/base/{{cookiecutter.__project_slug}}/docs/concepts/index.rst
reps/templates/base/{{cookiecutter.__project_slug}}/docs/conf.py
reps/templates/base/{{cookiecutter.__project_slug}}/docs/howto/index.rst
reps/templates/base/{{cookiecutter.__project_slug}}/docs/index.rst
reps/templates/base/{{cookiecutter.__project_slug}}/docs/reference/index.rst
reps/templates/base/{{cookiecutter.__project_slug}}/docs/tutorials/index.rst
reps/templates/python/cookiecutter.json
reps/templates/python/hooks/post_gen_project.py
reps/templates/python/hooks/pre_gen_project.py
reps/templates/python/{{cookiecutter.__project_slug}}/.gitignore
reps/templates/python/{{cookiecutter.__project_slug}}/.taskcluster.yml
reps/templates/python/{{cookiecutter.__project_slug}}/pyproject.toml
reps/templates/python/{{cookiecutter.__project_slug}}/src/{{cookiecutter.__package_name}}/__init__.py
reps/templates/python/{{cookiecutter.__project_slug}}/taskcluster/ci/codecov/kind.yml
reps/templates/python/{{cookiecutter.__project_slug}}/taskcluster/ci/config.yml
reps/templates/python/{{cookiecutter.__project_slug}}/taskcluster/ci/docker-image/kind.yml
reps/templates/python/{{cookiecutter.__project_slug}}/taskcluster/ci/fetch/kind.yml
reps_new-0.3.6.dist-info/LICENSE
reps_new-0.3.6.dist-info/METADATA
reps_new-0.3.6.dist-info/WHEEL
reps_new-0.3.6.dist-info/entry_points.txt
reps_new-0.3.6.dist-info/RECORD
