Metadata-Version: 2.1
Name: reps-new
Version: 0.3.6
Summary: Mozilla Release Engineering Project Standard
License: MPL-2.0
Author: Mozilla Release Engineering
Author-email: release@mozilla.com
Requires-Python: >=3.8,<4.0
Classifier: License :: OSI Approved
Classifier: Programming Language :: Python :: 3
Classifier: Programming Language :: Python :: 3.8
Classifier: Programming Language :: Python :: 3.9
Classifier: Programming Language :: Python :: 3.10
Classifier: Programming Language :: Python :: 3.11
Classifier: Programming Language :: Python :: 3.12
Requires-Dist: cookiecutter (>=2.1.1,<3.0.0)
Requires-Dist: halo (>=0.0.31,<0.0.32)
Requires-Dist: pip-tools (>=6.14.0,<7.0.0)
Requires-Dist: pre-commit (>=3.3.3,<4.0.0)
Requires-Dist: ruamel-yaml (>=0.17.32,<0.18.0)
Requires-Dist: taskcluster-taskgraph (>=5.4.0,<6.0.0)
